README.md
setup.py
workerwork/__init__.py
workerwork/models.py
workerwork.egg-info/PKG-INFO
workerwork.egg-info/SOURCES.txt
workerwork.egg-info/dependency_links.txt
workerwork.egg-info/requires.txt
workerwork.egg-info/top_level.txt