Metadata-Version: 1.0
Name: workerwork
Version: 0.0.1
Summary: a library for wow Developer
Home-page: UNKNOWN
Author: workerwork
Author-email: workerwork@qq.com
License: MIT License
Keywords: wow
Platform: any
